LICENSE
README.md
setup.py
happychat/__init__.py
happychat/happychat.py
happychat.egg-info/PKG-INFO
happychat.egg-info/SOURCES.txt
happychat.egg-info/dependency_links.txt
happychat.egg-info/entry_points.txt
happychat.egg-info/requires.txt
happychat.egg-info/top_level.txt