Metadata-Version: 2.1
Name: happychat
Version: 0.0.1
Summary: Unsecure chatting app using email.
Home-page: https://github.com/kacirekj/happychat
Author: Jiri Kacirek
Author-email: kacirek.j@gmail.com
License: UNKNOWN
Platform: UNKNOWN
Classifier: Programming Language :: Python :: 3
Classifier: License :: OSI Approved :: MIT License
Classifier: Operating System :: OS Independent
Requires-Python: >=3.6
License-File: LICENSE
